.DS_Store
gpsparser.py
gpsparser/__init__.py
gpsparser/gpsparser.py
gpsparser/setup.py
gpsparser-0.3.1.dist-info/DESCRIPTION.rst
gpsparser-0.3.1.dist-info/METADATA
gpsparser-0.3.1.dist-info/RECORD
gpsparser-0.3.1.dist-info/WHEEL
gpsparser-0.3.1.dist-info/metadata.json
gpsparser-0.3.1.dist-info/top_level.txt
gpsparser-0.3.1.dist-info/zip-safe
