Metadata-Version: 2.0
Name: gpsparser
Version: 0.3.1
Summary: gpsparser is a package for the parsing of GPS NMEA strings.
Home-page: UNKNOWN
Author: Val Schmidt
Author-email: vschmidt@ccom.unh.edu
License: GPL
Platform: UNKNOWN
